tyke/__init__.py
tyke/env_var_settings.py
tyke/version.py
tyke/agent/__init__.py
tyke/agent/constants.py
tyke/agent/custom_logger.py
tyke/agent/autoinstrumentation/__init__.py
tyke/agent/autoinstrumentation/sitecustomize.py
tyke/agent/autoinstrumentation/tyke_instrument.py
tyke/agent/config/__init__.py
tyke/agent/config/config_pb2.py
tyke/agent/config/default.py
tyke/agent/config/environment.py
tyke/agent/config/file.py
tyke/agent/filter/__init__.py
tyke/agent/filter/registry.py
tyke/agent/init/__init__.py
tyke/agent/instrumentation/__init__.py
tyke/agent/instrumentation/instrumentation_definitions.py
tyke/agent/instrumentation/aiohttp/__init__.py
tyke/agent/instrumentation/aiopg/__init__.py
tyke/agent/instrumentation/asyncpg/__init__.py
tyke/agent/instrumentation/aws_lambda/__init__.py
tyke/agent/instrumentation/boto/__init__.py
tyke/agent/instrumentation/botocore/__init__.py
tyke/agent/instrumentation/cassandra/__init__.py
tyke/agent/instrumentation/celery/__init__.py
tyke/agent/instrumentation/confluent_kafka/__init__.py
tyke/agent/instrumentation/django/__init__.py
tyke/agent/instrumentation/django/django_auto_instrumentation_compat.py
tyke/agent/instrumentation/elasticsearch/__init__.py
tyke/agent/instrumentation/fastapi/__init__.py
tyke/agent/instrumentation/fastapi/fast_api_auto_instrumentation_compat.py
tyke/agent/instrumentation/flask/__init__.py
tyke/agent/instrumentation/grpc/__init__.py
tyke/agent/instrumentation/httpx/__init__.py
tyke/agent/instrumentation/kafka_python/__init__.py
tyke/agent/instrumentation/method/__init__.py
tyke/agent/instrumentation/mysql/__init__.py
tyke/agent/instrumentation/mysqlclient/__init__.py
tyke/agent/instrumentation/postgresql/__init__.py
tyke/agent/instrumentation/postgresql_binary/__init__.py
tyke/agent/instrumentation/pymongo/__init__.py
tyke/agent/instrumentation/pymysql/__init__.py
tyke/agent/instrumentation/redis/__init__.py
tyke/agent/instrumentation/remoulade/__init__.py
tyke_agent-0.2.2.dist-info/LICENSE
tyke_agent-0.2.2.dist-info/METADATA
tyke_agent-0.2.2.dist-info/WHEEL
tyke_agent-0.2.2.dist-info/entry_points.txt
tyke_agent-0.2.2.dist-info/top_level.txt
tyke_agent-0.2.2.dist-info/RECORD
