Metadata-Version: 2.1
Name: tyke-agent
Version: 0.2.2
Summary: Tyke Python Agent
Home-page: https://tyke.ai
Author: TykeVision
Author-email: tech@tyke.ai
Project-URL: Bug Tracker, https://github.com/tykevision/python-agent/issues
Keywords: Tyke Python agent instrumentation
Classifier: Programming Language :: Python :: 3
Classifier: Programming Language :: Python :: 3.7
Classifier: Programming Language :: Python :: 3.8
Classifier: Programming Language :: Python :: 3.9
Classifier: Programming Language :: Python :: 3.10
Classifier: Programming Language :: Python :: 3.11
Classifier: License :: OSI Approved :: Apache Software License
Classifier: Operating System :: OS Independent
Requires-Python: >=3.7
License-File: LICENSE
Requires-Dist: opentelemetry-api ==1.20.0
Requires-Dist: opentelemetry-exporter-otlp ==1.20.0
Requires-Dist: opentelemetry-exporter-zipkin ==1.20.0
Requires-Dist: opentelemetry-instrumentation ==0.41b0
Requires-Dist: opentelemetry-instrumentation-aiohttp-client ==0.41b0
Requires-Dist: opentelemetry-instrumentation-aiopg ==0.41b0
Requires-Dist: opentelemetry-instrumentation-asgi ==0.41b0
Requires-Dist: opentelemetry-instrumentation-asyncpg ==0.41b0
Requires-Dist: opentelemetry-instrumentation-aws-lambda ==0.41b0
Requires-Dist: opentelemetry-instrumentation-boto ==0.41b0
Requires-Dist: opentelemetry-instrumentation-botocore ==0.41b0
Requires-Dist: opentelemetry-instrumentation-cassandra ==0.41b0
Requires-Dist: opentelemetry-instrumentation-celery ==0.41b0
Requires-Dist: opentelemetry-instrumentation-confluent-kafka ==0.41b0
Requires-Dist: opentelemetry-instrumentation-django ==0.41b0
Requires-Dist: opentelemetry-instrumentation-elasticsearch ==0.41b0
Requires-Dist: opentelemetry-instrumentation-fastapi ==0.41b0
Requires-Dist: opentelemetry-instrumentation-flask ==0.41b0
Requires-Dist: opentelemetry-instrumentation-grpc ==0.41b0
Requires-Dist: opentelemetry-instrumentation-httpx ==0.41b0
Requires-Dist: opentelemetry-instrumentation-kafka-python ==0.41b0
Requires-Dist: opentelemetry-instrumentation-mysql ==0.41b0
Requires-Dist: opentelemetry-instrumentation-mysqlclient ==0.41b0
Requires-Dist: opentelemetry-instrumentation-psycopg2 ==0.41b0
Requires-Dist: opentelemetry-instrumentation-pymongo ==0.41b0
Requires-Dist: opentelemetry-instrumentation-pymysql ==0.41b0
Requires-Dist: opentelemetry-instrumentation-redis ==0.41b0
Requires-Dist: opentelemetry-instrumentation-remoulade ==0.41b0
Requires-Dist: opentelemetry-instrumentation-requests ==0.41b0
Requires-Dist: opentelemetry-instrumentation-sklearn ==0.41b0
Requires-Dist: opentelemetry-instrumentation-sqlalchemy ==0.41b0
Requires-Dist: opentelemetry-instrumentation-urllib3 ==0.41b0
Requires-Dist: opentelemetry-instrumentation-urllib ==0.41b0
Requires-Dist: opentelemetry-instrumentation-wsgi ==0.41b0
Requires-Dist: opentelemetry-propagator-b3 ==1.20.0
Requires-Dist: opentelemetry-sdk ==1.20.0
Requires-Dist: opentelemetry-util-http ==0.41b0
Requires-Dist: deprecated ==1.2.12
Requires-Dist: google >=3.0.0
Requires-Dist: pyyaml
Requires-Dist: protobuf >=3.20.1
